setup.py
plotwhynot/__init__.py
plotwhynot/_figure.py
plotwhynot/_math.py
plotwhynot.egg-info/PKG-INFO
plotwhynot.egg-info/SOURCES.txt
plotwhynot.egg-info/dependency_links.txt
plotwhynot.egg-info/top_level.txt
plotwhynot/_utils/__init__.py
plotwhynot/_utils/_constants.py
plotwhynot/_utils/_grouping.py
plotwhynot/_utils/_protocol.py
plotwhynot/_utils/_utils.py
plotwhynot/animation/__init__.py
plotwhynot/animation/_basic/__init__.py
plotwhynot/animation/_basic/_animation.py
plotwhynot/animation/_basic/_axis_limiting.py
plotwhynot/animation/_basic/_camera_rotation.py
plotwhynot/animation/_basic/_color.py
plotwhynot/animation/_basic/_coordinates.py
plotwhynot/animation/_basic/_line.py
plotwhynot/animation/_basic/_rotation.py
plotwhynot/animation/_basic/_scale.py
plotwhynot/animation/_basic/_sleep.py
plotwhynot/animation/_basic/_text.py
plotwhynot/animation/advanced/__init__.py