Metadata-Version: 2.1
Name: plotwhynot
Version: 0.1.0
Summary: Convenient animation for matplotlib
Author: Andrei Ignatov
Author-email: rayignatov@outlook.com
Classifier: Programming Language :: Python :: 3
Classifier: License :: OSI Approved :: MIT License
Classifier: Operating System :: OS Independent
Requires-Python: >=3.6
